[{"name": "super()", "repo": "mlvc-lab/Classification-NAS", "file_in_repo": "Auto-Keras/autokeras/hypermodels/wrapper.py", "parent_function": "__init__", "file": "wrapper.py", "params": null, "repo_version": "latest"}, {"name": "super", "repo": "mlvc-lab/Classification-NAS", "file_in_repo": "Auto-Keras/autokeras/hypermodels/wrapper.py", "parent_function": "__init__", "file": "wrapper.py", "params": null, "repo_version": "latest"}, {"name": "super()", "repo": "mlvc-lab/Classification-NAS", "file_in_repo": "Auto-Keras/autokeras/hypermodels/wrapper.py", "parent_function": "get_config", "file": "wrapper.py", "params": null, "repo_version": "latest"}, {"name": "super", "repo": "mlvc-lab/Classification-NAS", "file_in_repo": "Auto-Keras/autokeras/hypermodels/wrapper.py", "parent_function": "get_config", "file": "wrapper.py", "params": null, "repo_version": "latest"}, {"name": "config.update", "repo": "mlvc-lab/Classification-NAS", "file_in_repo": "Auto-Keras/autokeras/hypermodels/wrapper.py", "parent_function": "get_config", "file": "wrapper.py", "params": null, "repo_version": "latest"}, {"name": "nest.flatten", "repo": "mlvc-lab/Classification-NAS", "file_in_repo": "Auto-Keras/autokeras/hypermodels/wrapper.py", "parent_function": "build", "file": "wrapper.py", "params": null, "repo_version": "latest"}, {"name": "hp.Choice", "repo": "mlvc-lab/Classification-NAS", "file_in_repo": "Auto-Keras/autokeras/hypermodels/wrapper.py", "parent_function": "build", "file": "wrapper.py", "params": null, "repo_version": "latest"}, {"name": "hp.Boolean", "repo": "mlvc-lab/Classification-NAS", "file_in_repo": "Auto-Keras/autokeras/hypermodels/wrapper.py", "parent_function": "build", "file": "wrapper.py", "params": null, "repo_version": "latest"}, {"name": "hp.Boolean", "repo": "mlvc-lab/Classification-NAS", "file_in_repo": "Auto-Keras/autokeras/hypermodels/wrapper.py", "parent_function": "build", "file": "wrapper.py", "params": null, "repo_version": "latest"}, {"name": "preprocessing.Normalization()", "repo": "mlvc-lab/Classification-NAS", "file_in_repo": "Auto-Keras/autokeras/hypermodels/wrapper.py", "parent_function": "build", "file": "wrapper.py", "params": null, "repo_version": "latest"}, {"name": "preprocessing.Normalization", "repo": "mlvc-lab/Classification-NAS", "file_in_repo": "Auto-Keras/autokeras/hypermodels/wrapper.py", "parent_function": "build", "file": "wrapper.py", "params": null, "repo_version": "latest"}, {"name": "preprocessing.ImageAugmentation()", "repo": "mlvc-lab/Classification-NAS", "file_in_repo": "Auto-Keras/autokeras/hypermodels/wrapper.py", "parent_function": "build", "file": "wrapper.py", "params": null, "repo_version": "latest"}, {"name": "preprocessing.ImageAugmentation", "repo": "mlvc-lab/Classification-NAS", "file_in_repo": "Auto-Keras/autokeras/hypermodels/wrapper.py", "parent_function": "build", "file": "wrapper.py", "params": null, "repo_version": "latest"}, {"name": "basic.ResNetBlock()", "repo": "mlvc-lab/Classification-NAS", "file_in_repo": "Auto-Keras/autokeras/hypermodels/wrapper.py", "parent_function": "build", "file": "wrapper.py", "params": null, "repo_version": "latest"}, {"name": "basic.ResNetBlock", "repo": "mlvc-lab/Classification-NAS", "file_in_repo": "Auto-Keras/autokeras/hypermodels/wrapper.py", "parent_function": "build", "file": "wrapper.py", "params": null, "repo_version": "latest"}, {"name": "basic.XceptionBlock()", "repo": "mlvc-lab/Classification-NAS", "file_in_repo": "Auto-Keras/autokeras/hypermodels/wrapper.py", "parent_function": "build", "file": "wrapper.py", "params": null, "repo_version": "latest"}, {"name": "basic.XceptionBlock", "repo": "mlvc-lab/Classification-NAS", "file_in_repo": "Auto-Keras/autokeras/hypermodels/wrapper.py", "parent_function": "build", "file": "wrapper.py", "params": null, "repo_version": "latest"}, {"name": "basic.ConvBlock()", "repo": "mlvc-lab/Classification-NAS", "file_in_repo": "Auto-Keras/autokeras/hypermodels/wrapper.py", "parent_function": "build", "file": "wrapper.py", "params": null, "repo_version": "latest"}, {"name": "basic.ConvBlock", "repo": "mlvc-lab/Classification-NAS", "file_in_repo": "Auto-Keras/autokeras/hypermodels/wrapper.py", "parent_function": "build", "file": "wrapper.py", "params": null, "repo_version": "latest"}, {"name": "super()", "repo": "mlvc-lab/Classification-NAS", "file_in_repo": "Auto-Keras/autokeras/hypermodels/wrapper.py", "parent_function": "__init__", "file": "wrapper.py", "params": null, "repo_version": "latest"}, {"name": "super", "repo": "mlvc-lab/Classification-NAS", "file_in_repo": "Auto-Keras/autokeras/hypermodels/wrapper.py", "parent_function": "__init__", "file": "wrapper.py", "params": null, "repo_version": "latest"}, {"name": "super()", "repo": "mlvc-lab/Classification-NAS", "file_in_repo": "Auto-Keras/autokeras/hypermodels/wrapper.py", "parent_function": "get_config", "file": "wrapper.py", "params": null, "repo_version": "latest"}, {"name": "super", "repo": "mlvc-lab/Classification-NAS", "file_in_repo": "Auto-Keras/autokeras/hypermodels/wrapper.py", "parent_function": "get_config", "file": "wrapper.py", "params": null, "repo_version": "latest"}, {"name": "config.update", "repo": "mlvc-lab/Classification-NAS", "file_in_repo": "Auto-Keras/autokeras/hypermodels/wrapper.py", "parent_function": "get_config", "file": "wrapper.py", "params": null, "repo_version": "latest"}, {"name": "nest.flatten", "repo": "mlvc-lab/Classification-NAS", "file_in_repo": "Auto-Keras/autokeras/hypermodels/wrapper.py", "parent_function": "build", "file": "wrapper.py", "params": null, "repo_version": "latest"}, {"name": "hp.Choice", "repo": "mlvc-lab/Classification-NAS", "file_in_repo": "Auto-Keras/autokeras/hypermodels/wrapper.py", "parent_function": "build", "file": "wrapper.py", "params": null, "repo_version": "latest"}, {"name": "hp.Choice", "repo": "mlvc-lab/Classification-NAS", "file_in_repo": "Auto-Keras/autokeras/hypermodels/wrapper.py", "parent_function": "build", "file": "wrapper.py", "params": null, "repo_version": "latest"}, {"name": "preprocessing.TextToNgramVector(max_tokens=max_tokens)", "repo": "mlvc-lab/Classification-NAS", "file_in_repo": "Auto-Keras/autokeras/hypermodels/wrapper.py", "parent_function": "build", "file": "wrapper.py", "params": null, "repo_version": "latest"}, {"name": "preprocessing.TextToNgramVector", "repo": "mlvc-lab/Classification-NAS", "file_in_repo": "Auto-Keras/autokeras/hypermodels/wrapper.py", "parent_function": "build", "file": "wrapper.py", "params": null, "repo_version": "latest"}, {"name": "basic.DenseBlock()", "repo": "mlvc-lab/Classification-NAS", "file_in_repo": "Auto-Keras/autokeras/hypermodels/wrapper.py", "parent_function": "build", "file": "wrapper.py", "params": null, "repo_version": "latest"}, {"name": "basic.DenseBlock", "repo": "mlvc-lab/Classification-NAS", "file_in_repo": "Auto-Keras/autokeras/hypermodels/wrapper.py", "parent_function": "build", "file": "wrapper.py", "params": null, "repo_version": "latest"}, {"name": "preprocessing.TextToIntSequence(max_tokens=max_tokens)", "repo": "mlvc-lab/Classification-NAS", "file_in_repo": "Auto-Keras/autokeras/hypermodels/wrapper.py", "parent_function": "build", "file": "wrapper.py", "params": null, "repo_version": "latest"}, {"name": "preprocessing.TextToIntSequence", "repo": "mlvc-lab/Classification-NAS", "file_in_repo": "Auto-Keras/autokeras/hypermodels/wrapper.py", "parent_function": "build", "file": "wrapper.py", "params": null, "repo_version": "latest"}, {"name": "basic.ConvBlock()", "repo": "mlvc-lab/Classification-NAS", "file_in_repo": "Auto-Keras/autokeras/hypermodels/wrapper.py", "parent_function": "build", "file": "wrapper.py", "params": null, "repo_version": "latest"}, {"name": "basic.ConvBlock", "repo": "mlvc-lab/Classification-NAS", "file_in_repo": "Auto-Keras/autokeras/hypermodels/wrapper.py", "parent_function": "build", "file": "wrapper.py", "params": null, "repo_version": "latest"}, {"name": "reduction.SpatialReduction()", "repo": "mlvc-lab/Classification-NAS", "file_in_repo": "Auto-Keras/autokeras/hypermodels/wrapper.py", "parent_function": "build", "file": "wrapper.py", "params": null, "repo_version": "latest"}, {"name": "reduction.SpatialReduction", "repo": "mlvc-lab/Classification-NAS", "file_in_repo": "Auto-Keras/autokeras/hypermodels/wrapper.py", "parent_function": "build", "file": "wrapper.py", "params": null, "repo_version": "latest"}, {"name": "basic.DenseBlock()", "repo": "mlvc-lab/Classification-NAS", "file_in_repo": "Auto-Keras/autokeras/hypermodels/wrapper.py", "parent_function": "build", "file": "wrapper.py", "params": null, "repo_version": "latest"}, {"name": "basic.DenseBlock", "repo": "mlvc-lab/Classification-NAS", "file_in_repo": "Auto-Keras/autokeras/hypermodels/wrapper.py", "parent_function": "build", "file": "wrapper.py", "params": null, "repo_version": "latest"}, {"name": "super()", "repo": "mlvc-lab/Classification-NAS", "file_in_repo": "Auto-Keras/autokeras/hypermodels/wrapper.py", "parent_function": "__init__", "file": "wrapper.py", "params": null, "repo_version": "latest"}, {"name": "super", "repo": "mlvc-lab/Classification-NAS", "file_in_repo": "Auto-Keras/autokeras/hypermodels/wrapper.py", "parent_function": "__init__", "file": "wrapper.py", "params": null, "repo_version": "latest"}, {"name": "super()", "repo": "mlvc-lab/Classification-NAS", "file_in_repo": "Auto-Keras/autokeras/hypermodels/wrapper.py", "parent_function": "get_config", "file": "wrapper.py", "params": null, "repo_version": "latest"}, {"name": "super", "repo": "mlvc-lab/Classification-NAS", "file_in_repo": "Auto-Keras/autokeras/hypermodels/wrapper.py", "parent_function": "get_config", "file": "wrapper.py", "params": null, "repo_version": "latest"}, {"name": "config.update", "repo": "mlvc-lab/Classification-NAS", "file_in_repo": "Auto-Keras/autokeras/hypermodels/wrapper.py", "parent_function": "get_config", "file": "wrapper.py", "params": null, "repo_version": "latest"}, {"name": "hp.Choice", "repo": "mlvc-lab/Classification-NAS", "file_in_repo": "Auto-Keras/autokeras/hypermodels/wrapper.py", "parent_function": "build_categorical_encoding", "file": "wrapper.py", "params": null, "repo_version": "latest"}, {"name": "preprocessing.CategoricalToNumerical", "repo": "mlvc-lab/Classification-NAS", "file_in_repo": "Auto-Keras/autokeras/hypermodels/wrapper.py", "parent_function": "build_categorical_encoding", "file": "wrapper.py", "params": null, "repo_version": "latest"}, {"name": "block.build", "repo": "mlvc-lab/Classification-NAS", "file_in_repo": "Auto-Keras/autokeras/hypermodels/wrapper.py", "parent_function": "build_categorical_encoding", "file": "wrapper.py", "params": null, "repo_version": "latest"}, {"name": "basic.DenseBlock()", "repo": "mlvc-lab/Classification-NAS", "file_in_repo": "Auto-Keras/autokeras/hypermodels/wrapper.py", "parent_function": "build_body", "file": "wrapper.py", "params": null, "repo_version": "latest"}, {"name": "basic.DenseBlock", "repo": "mlvc-lab/Classification-NAS", "file_in_repo": "Auto-Keras/autokeras/hypermodels/wrapper.py", "parent_function": "build_body", "file": "wrapper.py", "params": null, "repo_version": "latest"}, {"name": "nest.flatten", "repo": "mlvc-lab/Classification-NAS", "file_in_repo": "Auto-Keras/autokeras/hypermodels/wrapper.py", "parent_function": "build", "file": "wrapper.py", "params": null, "repo_version": "latest"}, {"name": "self.build_categorical_encoding", "repo": "mlvc-lab/Classification-NAS", "file_in_repo": "Auto-Keras/autokeras/hypermodels/wrapper.py", "parent_function": "build", "file": "wrapper.py", "params": null, "repo_version": "latest"}, {"name": "self.build_body", "repo": "mlvc-lab/Classification-NAS", "file_in_repo": "Auto-Keras/autokeras/hypermodels/wrapper.py", "parent_function": "build", "file": "wrapper.py", "params": null, "repo_version": "latest"}, {"name": "super()", "repo": "mlvc-lab/Classification-NAS", "file_in_repo": "Auto-Keras/autokeras/hypermodels/wrapper.py", "parent_function": "__init__", "file": "wrapper.py", "params": null, "repo_version": "latest"}, {"name": "super", "repo": "mlvc-lab/Classification-NAS", "file_in_repo": "Auto-Keras/autokeras/hypermodels/wrapper.py", "parent_function": "__init__", "file": "wrapper.py", "params": null, "repo_version": "latest"}, {"name": "super()", "repo": "mlvc-lab/Classification-NAS", "file_in_repo": "Auto-Keras/autokeras/hypermodels/wrapper.py", "parent_function": "get_config", "file": "wrapper.py", "params": null, "repo_version": "latest"}, {"name": "super", "repo": "mlvc-lab/Classification-NAS", "file_in_repo": "Auto-Keras/autokeras/hypermodels/wrapper.py", "parent_function": "get_config", "file": "wrapper.py", "params": null, "repo_version": "latest"}, {"name": "nest.flatten", "repo": "mlvc-lab/Classification-NAS", "file_in_repo": "Auto-Keras/autokeras/hypermodels/wrapper.py", "parent_function": "build", "file": "wrapper.py", "params": null, "repo_version": "latest"}, {"name": "basic.RNNBlock()", "repo": "mlvc-lab/Classification-NAS", "file_in_repo": "Auto-Keras/autokeras/hypermodels/wrapper.py", "parent_function": "build", "file": "wrapper.py", "params": null, "repo_version": "latest"}, {"name": "basic.RNNBlock", "repo": "mlvc-lab/Classification-NAS", "file_in_repo": "Auto-Keras/autokeras/hypermodels/wrapper.py", "parent_function": "build", "file": "wrapper.py", "params": null, "repo_version": "latest"}]