{"repo": "automl/Auto-PyTorch", "imports": [{"name": "logging", "module": null, "asname": null}, {"name": "numpy", "module": null, "asname": "np"}, {"name": "sys", "module": null, "asname": null}, {"name": "PipelineNode", "module": "autoPyTorch.pipeline.base.pipeline_node", "asname": null}, {"name": "parse_hyperparameter_search_space_updates", "module": "autoPyTorch.utils.hyperparameter_search_space_update", "asname": null}, {"name": "ConfigOption", "module": "autoPyTorch.utils.config.config_option", "asname": null}, {"name": "to_bool", "module": "autoPyTorch.utils.config.config_option", "asname": null}, {"name": "json_result_logger", "module": "hpbandster.core.result", "asname": null}], "file_in_repo": "autoPyTorch/pipeline/nodes/autonet_settings.py", "repo_version": "v0.0.2", "file": "autonet_settings.py"}