[{"name": "range", "repo": "hidibelan/jjp1", "file_in_repo": "python/ray/tune/examples/sigopt_example.py", "parent_function": "easy_objective", "file": "sigopt_example.py", "params": null, "repo_version": "ray-1.2.0"}, {"name": "evaluate", "repo": "hidibelan/jjp1", "file_in_repo": "python/ray/tune/examples/sigopt_example.py", "parent_function": "easy_objective", "file": "sigopt_example.py", "params": null, "repo_version": "ray-1.2.0"}, {"name": "tune.report", "repo": "hidibelan/jjp1", "file_in_repo": "python/ray/tune/examples/sigopt_example.py", "parent_function": "easy_objective", "file": "sigopt_example.py", "params": null, "repo_version": "ray-1.2.0"}, {"name": "time.sleep", "repo": "hidibelan/jjp1", "file_in_repo": "python/ray/tune/examples/sigopt_example.py", "parent_function": "easy_objective", "file": "sigopt_example.py", "params": null, "repo_version": "ray-1.2.0"}, {"name": "argparse.ArgumentParser", "repo": "hidibelan/jjp1", "file_in_repo": "python/ray/tune/examples/sigopt_example.py", "parent_function": null, "file": "sigopt_example.py", "params": null, "repo_version": "ray-1.2.0"}, {"name": "parser.add_argument", "repo": "hidibelan/jjp1", "file_in_repo": "python/ray/tune/examples/sigopt_example.py", "parent_function": null, "file": "sigopt_example.py", "params": null, "repo_version": "ray-1.2.0"}, {"name": "parser.parse_known_args", "repo": "hidibelan/jjp1", "file_in_repo": "python/ray/tune/examples/sigopt_example.py", "parent_function": null, "file": "sigopt_example.py", "params": null, "repo_version": "ray-1.2.0"}, {"name": "sys.exit", "repo": "hidibelan/jjp1", "file_in_repo": "python/ray/tune/examples/sigopt_example.py", "parent_function": null, "file": "sigopt_example.py", "params": null, "repo_version": "ray-1.2.0"}, {"name": "ValueError", "repo": "hidibelan/jjp1", "file_in_repo": "python/ray/tune/examples/sigopt_example.py", "parent_function": null, "file": "sigopt_example.py", "params": null, "repo_version": "ray-1.2.0"}, {"name": "SigOptSearch", "repo": "hidibelan/jjp1", "file_in_repo": "python/ray/tune/examples/sigopt_example.py", "parent_function": null, "file": "sigopt_example.py", "params": null, "repo_version": "ray-1.2.0"}, {"name": "AsyncHyperBandScheduler", "repo": "hidibelan/jjp1", "file_in_repo": "python/ray/tune/examples/sigopt_example.py", "parent_function": null, "file": "sigopt_example.py", "params": null, "repo_version": "ray-1.2.0"}, {"name": "tune.run", "repo": "hidibelan/jjp1", "file_in_repo": "python/ray/tune/examples/sigopt_example.py", "parent_function": null, "file": "sigopt_example.py", "params": null, "repo_version": "ray-1.2.0"}, {"name": "analysis.get_best_config", "repo": "hidibelan/jjp1", "file_in_repo": "python/ray/tune/examples/sigopt_example.py", "parent_function": null, "file": "sigopt_example.py", "params": null, "repo_version": "ray-1.2.0"}]